digitalhub_data/__init__.py
digitalhub_data/datastores/__init__.py
digitalhub_data/datastores/builder.py
digitalhub_data/datastores/objects/__init__.py
digitalhub_data/datastores/objects/base.py
digitalhub_data/datastores/objects/local.py
digitalhub_data/datastores/objects/remote.py
digitalhub_data/datastores/objects/s3.py
digitalhub_data/datastores/objects/sql.py
digitalhub_data/entities/__init__.py
digitalhub_data/entities/entity_types.py
digitalhub_data/entities/registries.py
digitalhub_data/entities/dataitem/__init__.py
digitalhub_data/entities/dataitem/builder.py
digitalhub_data/entities/dataitem/crud.py
digitalhub_data/entities/dataitem/models.py
digitalhub_data/entities/dataitem/spec.py
digitalhub_data/entities/dataitem/status.py
digitalhub_data/entities/dataitem/entity/__init__.py
digitalhub_data/entities/dataitem/entity/_base.py
digitalhub_data/entities/dataitem/entity/dataitem.py
digitalhub_data/entities/dataitem/entity/iceberg.py
digitalhub_data/entities/dataitem/entity/table.py
digitalhub_data/entities/project/__init__.py
digitalhub_data/entities/project/builder.py
digitalhub_data/entities/project/crud.py
digitalhub_data/entities/project/spec.py
digitalhub_data/entities/project/entity/__init__.py
digitalhub_data/entities/project/entity/data.py
digitalhub_data/entities/run/__init__.py
digitalhub_data/entities/run/models.py
digitalhub_data/entities/run/spec.py
digitalhub_data/entities/run/status.py
digitalhub_data/readers/__init__.py
digitalhub_data/readers/builder.py
digitalhub_data/readers/registry.py
digitalhub_data/readers/objects/__init__.py
digitalhub_data/readers/objects/base.py
digitalhub_data/readers/objects/pandas.py
digitalhub_data/utils/__init__.py
digitalhub_data/utils/data_utils.py
digitalhub_data-0.7.0.dist-info/METADATA
digitalhub_data-0.7.0.dist-info/WHEEL
digitalhub_data-0.7.0.dist-info/top_level.txt
digitalhub_data-0.7.0.dist-info/RECORD
