Metadata-Version: 2.1
Name: digitalhub-data
Version: 0.7.0
Summary: Python SDK for DHCore data layer
Author-email: Fondazione Bruno Kessler <dslab@fbk.eu>, Matteo Martini <mmartini@fbk.eu>
Keywords: data,dataops,kubernetes
Classifier: License :: OSI Approved :: Apache Software License
Classifier: Programming Language :: Python :: 3.9
Classifier: Programming Language :: Python :: 3.10
Requires-Python: >=3.9
Requires-Dist: digitalhub-core<0.8,>=0.7.0b
Provides-Extra: pandas
Requires-Dist: pandas<2.2,>=1.2; extra == "pandas"
